README.md
setup.py
moduloprueba/__init__.py
moduloprueba/cal.py
moduloprueba.egg-info/PKG-INFO
moduloprueba.egg-info/SOURCES.txt
moduloprueba.egg-info/dependency_links.txt
moduloprueba.egg-info/top_level.txt