Metadata-Version: 2.1
Name: moduloprueba
Version: 0.1
Summary: Trabajo de modulos
Author: oscarchungara
Author-email: oscarunoja20@gmail.com
License: MIT
